<?xml version="1.0" encoding="utf-8" ?><dwsync><file name="buttons.bit" server="bongopress.co" local="3579596446" remote="3524356800" Dst="-1" /><file name="content.bit" server="bongopress.co" local="3579707498" remote="3579696660" Dst="-1" /><file name="description.bit" server="bongopress.co" local="3579596446" remote="3524356800" Dst="-1" /><file name="keywords.bit" server="bongopress.co" local="3579596446" remote="3524356800" Dst="-1" /><file name="nb_code.bit" server="bongopress.co" local="3579596446" remote="3524356800" Dst="-1" /><file name="nb_media.bit" server="bongopress.co" local="3579596446" remote="3524356800" Dst="-1" /><file name="position.bit" server="bongopress.co" local="3579596446" remote="3524356800" Dst="-1" /><file name="slug.bit" server="bongopress.co" local="3579596446" remote="3524356800" Dst="-1" /><file name="title.bit" server="bongopress.co" local="3579596447" remote="3524356800" Dst="-1" /></dwsync>